streamlit/__init__.py
streamlit/__main__.py
streamlit/beta_util.py
streamlit/bootstrap.py
streamlit/caching.py
streamlit/case_converters.py
streamlit/cli.py
streamlit/code_util.py
streamlit/config.py
streamlit/config_option.py
streamlit/config_util.py
streamlit/credentials.py
streamlit/cursor.py
streamlit/delta_generator.py
streamlit/development.py
streamlit/env_util.py
streamlit/error_util.py
streamlit/errors.py
streamlit/file_util.py
streamlit/folder_black_list.py
streamlit/forward_msg_cache.py
streamlit/git_util.py
streamlit/hashing.py
streamlit/js_number.py
streamlit/logger.py
streamlit/magic.py
streamlit/media_file_manager.py
streamlit/metrics.py
streamlit/metrics_util.py
streamlit/net_util.py
streamlit/policy.py
streamlit/report.py
streamlit/report_queue.py
streamlit/report_session.py
streamlit/report_thread.py
streamlit/script_request_queue.py
streamlit/script_runner.py
streamlit/secrets.py
streamlit/source_util.py
streamlit/string_util.py
streamlit/temporary_directory.py
streamlit/type_util.py
streamlit/uploaded_file_manager.py
streamlit/url_util.py
streamlit/util.py
streamlit/version.py
streamlit/commands/__init__.py
streamlit/commands/page_config.py
streamlit/components/__init__.py
streamlit/components/v1/__init__.py
streamlit/components/v1/component_arrow.py
streamlit/components/v1/components.py
streamlit/elements/__init__.py
streamlit/elements/alert.py
streamlit/elements/arrow.py
streamlit/elements/arrow_altair.py
streamlit/elements/arrow_vega_lite.py
streamlit/elements/balloons.py
streamlit/elements/bokeh_chart.py
streamlit/elements/button.py
streamlit/elements/checkbox.py
streamlit/elements/color_picker.py
streamlit/elements/dataframe_selector.py
streamlit/elements/deck_gl_json_chart.py
streamlit/elements/doc_string.py
streamlit/elements/empty.py
streamlit/elements/exception.py
streamlit/elements/file_uploader.py
streamlit/elements/form.py
streamlit/elements/graphviz_chart.py
streamlit/elements/iframe.py
streamlit/elements/image.py
streamlit_gcp-0.84.5.dist-info/METADATA
streamlit_gcp-0.84.5.dist-info/WHEEL
streamlit_gcp-0.84.5.dist-info/entry_points.txt
streamlit_gcp-0.84.5.dist-info/top_level.txt
streamlit_gcp-0.84.5.dist-info/RECORD
